quanturf/__init__.py
quanturf/__main__.py
quanturf/alphalab.ipynb
quanturf/chat.py
quanturf/config.yaml
quanturf/jupyter_notebook_config.py
quanturf/quanturf.ipynb
quanturf-8.6.7.data/data/version.py
quanturf-8.6.7.dist-info/LICENCE.txt
quanturf-8.6.7.dist-info/METADATA
quanturf-8.6.7.dist-info/WHEEL
quanturf-8.6.7.dist-info/entry_points.txt
quanturf-8.6.7.dist-info/top_level.txt
quanturf-8.6.7.dist-info/RECORD
