Metadata-Version: 2.1
Name: quanturf
Version: 8.6.7
Summary: REMOTE_USER Authenticator: An Authenticator for Jupyterhub to read user information from HTTP request headers, as when running behind an authenticating proxy.
Home-page: https://github.com/Quanturf/quanturf_pypi_package.git
Author: Quanturf
Author-email: quanturf.finance@gmail.com
License: GPLv3
Keywords: Interactive,Interpreter,Shell,Web
Platform: Linux
Platform: Mac OS X
Classifier: Intended Audience :: Developers
Classifier: Intended Audience :: System Administrators
Classifier: Intended Audience :: Science/Research
Classifier: License :: OSI Approved :: GNU General Public License v3 (GPLv3)
Classifier: Programming Language :: Python
Classifier: Programming Language :: Python :: 3
License-File: LICENCE.txt
Requires-Dist: jupyterlab ==3.6.3
Requires-Dist: jupyter-app-launcher ==0.1.6
Requires-Dist: typer ==0.9.0
Requires-Dist: maskpass ==0.3.7
Requires-Dist: openai ==0.27.0
Requires-Dist: ipython
